{
  "incidents": [
    {
      "id": "88568",
      "name": "ZU - [CG]REPOSIÇÃO MATERIAL",
      "location": "RS-ST01-31-02P-WCM01",
      "opened_at": "2026-04-17T11:49:24.163Z",
      "team": "LIMPEZA CONVENCIONAL"
    },
    {
      "id": "88569",
      "name": "ZU - [CG]RECOLHIMENTO RESÍDUOS",
      "location": "RS-ST01-28-00T-STR04",
      "opened_at": "2026-04-17T11:52:53.617Z",
      "team": "LIMPEZA CONVENCIONAL"
    },
    {
      "id": "88570",
      "name": "ZU - DESENTUPIMENTO VASO",
      "location": "RS-ST01-31-02P-WCM01",
      "opened_at": "2026-04-17T11:56:45.677Z",
      "team": "CIVIL"
    },
    {
      "id": "88574",
      "name": "ZU - POCETO - VAZAMENTO",
      "location": "RS-ST01-31-01S-STR01",
      "opened_at": "2026-04-17T12:17:34.280Z",
      "team": "UTILIDADES"
    }
  ]
}
